altvmasterlist/__init__.py
altvmasterlist/enum.py
altvmasterlist/exceptions.py
altvmasterlist/masterlist.py
altvmasterlist-4.0.0.dist-info/LICENSE
altvmasterlist-4.0.0.dist-info/METADATA
altvmasterlist-4.0.0.dist-info/WHEEL
altvmasterlist-4.0.0.dist-info/RECORD
