Metadata-Version: 2.3
Name: altvmasterlist
Version: 4.0.0
Summary: A package to use the alt:V Masterlist api.
License: MPL-2.0
Author: Nickwasused
Author-email: contact.nickwasused.fa6c8@simplelogin.co
Requires-Python: >=3.10
Classifier: License :: OSI Approved
Classifier: License :: OSI Approved :: Mozilla Public License 2.0 (MPL 2.0)
Classifier: Operating System :: OS Independent
Classifier: Programming Language :: Python :: 3
Classifier: Programming Language :: Python :: 3.10
Classifier: Programming Language :: Python :: 3.11
Classifier: Programming Language :: Python :: 3.12
Classifier: Programming Language :: Python :: 3.13
Classifier: Programming Language :: Python :: 3 :: Only
Requires-Dist: requests (>=2.31.0,<3.0.0)
Project-URL: Bug Tracker, https://github.com/Nickwasused/altv-python-masterlist/issues
Project-URL: Documentation, https://nickwasused.github.io/altv-python-masterlist/
Project-URL: Repository, https://github.com/Nickwasused/altv-python-masterlist
